azure/mgmt/orbital/__init__.py
azure/mgmt/orbital/_azure_orbital.py
azure/mgmt/orbital/_configuration.py
azure/mgmt/orbital/_patch.py
azure/mgmt/orbital/_serialization.py
azure/mgmt/orbital/_vendor.py
azure/mgmt/orbital/_version.py
azure/mgmt/orbital/py.typed
azure/mgmt/orbital/aio/__init__.py
azure/mgmt/orbital/aio/_azure_orbital.py
azure/mgmt/orbital/aio/_configuration.py
azure/mgmt/orbital/aio/_patch.py
azure/mgmt/orbital/aio/operations/__init__.py
azure/mgmt/orbital/aio/operations/_available_ground_stations_operations.py
azure/mgmt/orbital/aio/operations/_contact_profiles_operations.py
azure/mgmt/orbital/aio/operations/_contacts_operations.py
azure/mgmt/orbital/aio/operations/_operations.py
azure/mgmt/orbital/aio/operations/_operations_results_operations.py
azure/mgmt/orbital/aio/operations/_patch.py
azure/mgmt/orbital/aio/operations/_spacecrafts_operations.py
azure/mgmt/orbital/models/__init__.py
azure/mgmt/orbital/models/_azure_orbital_enums.py
azure/mgmt/orbital/models/_models_py3.py
azure/mgmt/orbital/models/_patch.py
azure/mgmt/orbital/operations/__init__.py
azure/mgmt/orbital/operations/_available_ground_stations_operations.py
azure/mgmt/orbital/operations/_contact_profiles_operations.py
azure/mgmt/orbital/operations/_contacts_operations.py
azure/mgmt/orbital/operations/_operations.py
azure/mgmt/orbital/operations/_operations_results_operations.py
azure/mgmt/orbital/operations/_patch.py
azure/mgmt/orbital/operations/_spacecrafts_operations.py
azure_mgmt_orbital-2.0.0.dist-info/LICENSE
azure_mgmt_orbital-2.0.0.dist-info/LICENSE.txt
azure_mgmt_orbital-2.0.0.dist-info/METADATA
azure_mgmt_orbital-2.0.0.dist-info/WHEEL
azure_mgmt_orbital-2.0.0.dist-info/top_level.txt
azure_mgmt_orbital-2.0.0.dist-info/RECORD
